tests/__init__.py
tests/test_counter.py
visitorcounter/__init__.py
visitorcounter/counter.py
visitorcounter-0.2.1.dist-info/LICENSE
visitorcounter-0.2.1.dist-info/METADATA
visitorcounter-0.2.1.dist-info/WHEEL
visitorcounter-0.2.1.dist-info/top_level.txt
visitorcounter-0.2.1.dist-info/RECORD
