Metadata-Version: 2.1
Name: visitorcounter
Version: 0.2.1
Summary: Vistor counter calculation
Author: Sandeep Reddy P 
Author-email: sandeepreddy.pathakottu@gmail.com
License: MIT
Classifier: Development Status :: 3 - Alpha
Classifier: Intended Audience :: Developers
Classifier: License :: OSI Approved :: MIT License
Classifier: Programming Language :: Python :: 3
Classifier: Programming Language :: Python :: 3.7
Classifier: Programming Language :: Python :: 3.8
Classifier: Programming Language :: Python :: 3.9
Requires-Python: >=3.7
License-File: LICENSE
